upander/FireStorage.py
upander/UploaderBase.py
upander/__init__.py
upander/ファイルなう.py
upander-0.1.3.dist-info/METADATA
upander-0.1.3.dist-info/WHEEL
upander-0.1.3.dist-info/top_level.txt
upander-0.1.3.dist-info/RECORD
