Metadata-Version: 2.1
Name: upander
Version: 0.1.3
Summary: UNKNOWN
Home-page: https://github.com/Panda1000000/upander
Author: Panda
Author-email: aaa@example.com
Maintainer: Panda
Maintainer-email: aaa@example.com
License: Apache License 2.0
Download-URL: https://github.com/Panda1000000/upander
Platform: UNKNOWN
Classifier: Programming Language :: Python :: 3 :: Only
Requires-Python: >=3.6
Requires-Dist: requests (==2.25.1)
